Workbook

Sheet README
A1: PATHYAM — Nutrition Data Source Comparison
A2: Companion to PATHYAM_RESEARCH_DOSSIER.md · Regional South Indian calorie & nutrition tracker (Tamil · Telugu · Malayalam · Kannada)
A3: Built 12 August 2026
A6: WHAT THIS WORKBOOK IS FOR
B7: A decision tool for choosing which nutrition data sources Pathyam builds on, and for tracking the legal work that has to happen before any of them can be used commercially.
A9: TABS
A10: Weights | B10: The ten scoring criteria and their weights. THIS IS THE ONLY TAB YOU EDIT to re-run the analysis. Change a weight in the yellow cells and every score and rank on 'Scoring Matrix' updates.
A11: Scoring Matrix | B11: 25 candidate data sources scored 0–5 on each criterion, weighted, ranked. Scores are editable; the weighted total, score % and rank are formulas.
A12: Source Master | B12: All 36 sources catalogued — including the ones deliberately NOT scored (regulators, reference standards, surveys, tooling), with a note explaining why each was excluded.
A13: Licence & Risk | B13: Licence terms, risk level, specific hazard, mitigation and required action per source. Read the top two rows before anything else.
A14: Acquisition Tracker | B14: 15 sequenced actions with owner, target week and status. Update the Status column as you go.
A16: HOW THE SCORE WORKS
B17: Weighted score (0–5) = SUMPRODUCT(the source's ten scores, the ten weights)
B18: Score % = weighted score ÷ 5. Rank is descending by weighted score.
B19: Weights sum to 100%. The default weighting reflects the agreed strategy: dataset-first, South-Indian-specific, provenance as the moat. South Indian coverage carries the heaviest weight (25%) because a source with excellent data and zero South Indian relevance cannot be primary, however good it is.
A21: HOW TO READ THE RANKING
B22: The ranking answers one question: 'which source should Pathyam build its core dataset on?' It does NOT rank sources by quality in the abstract. USDA FoodData Central is a better-engineered database than anything in India and still ranks mid-table here, because it contains no South Indian food. That is the correct answer to the question being asked.
B23: A LOW RANK DOES NOT MEAN DISPENSABLE. Three sources rank in the bottom half and are still mandatory: the USDA Nutrient Retention Factors (R6), the FAO/INFOODS guidelines, and Bognár's yield tables. They score near zero on coverage criteria because they contain no foods at all — they are cooking factors and methodology. You cannot compute a single cooked dish without them. Read the Verdict column, not just the rank.
B24: Two rows are included specifically because they are instructive rather than usable:
B25: · HealthifyMe scores maximum on coverage and zero on provenance and licence — the clearest possible demonstration that breadth alone is not a moat.
B26: · Open Food Facts scores well on access and badly on licence — it is a hazard, not a resource. See Licence & Risk.
A28: COLOUR CONVENTION
B29: Yellow fill = you edit this. Blue text = hardcoded input. Green text = links to another sheet. Black = formula.
A31: THE TWO THINGS THAT MATTER MOST
B32: 1. The ICMR-NIN licence position is unresolved and everything downstream depends on it. Send the letter this week.
B33: 2. Open Food Facts' ODbL share-alike clause would force you to open-source Pathyam-DB if it is ever merged into the core table. Architect the separation before anyone writes an ingestion script.

Sheet Weights
A1: Scoring criteria and weights
A2: Edit the yellow cells only. Weights must sum to 100% — the check cell below turns red if they do not.
A4: ID | B4: Criterion | C4: Weight | D4: What a 5 means / how to score
A5: C1 | B5: South Indian coverage | C5: 0.25 | D5: Does it contain Tamil/Telugu/Malayalam/Kannada foods, ingredients or dishes — and are regional variants distinguishable?
A6: C2 | B6: Recipe / cooked-dish level | C6: 0.13 | D6: Cooked, composite dishes as consumed — not just raw ingredients. 0 = raw only, 5 = full recipe database.
A7: C3 | B7: Per-serving & household units | C7: 0.08 | D7: Serving sizes, katori/count-based units, edible portion weights. Not just per-100g.
A8: C4 | B8: Micronutrient / component depth | C8: 0.09 | D8: Beyond macros: vitamins, minerals, fatty acids, amino acids, polyphenols, phytate.
A9: C5 | B9: Provenance & method docs | C9: 0.13 | D9: Is each value traceable to a sampling plan, analytical method and citation?
A10: C6 | B10: Commercial licence clarity | C10: 0.15 | D10: 5 = clean permissive/public domain. 0 = unusable or legally hazardous (incl. share-alike contamination).
A11: C7 | B11: Machine readability / API | C11: 0.07 | D11: Structured download or API vs PDF-only. 0 = PDF/print, 5 = documented API + bulk files.
A12: C8 | B12: Maintenance & update cadence | C12: 0.04 | D12: Is it actively updated, or frozen at publication?
A13: C9 | B13: Regional-language support | C13: 0.04 | D13: Native-script or romanised food names in ta/te/ml/kn.
A14: C10 | B14: Cost to acquire (5 = free) | C14: 0.02 | D14: 5 = free/open. 1 = enterprise contract. Acquisition cost only, not integration effort.
B15: TOTAL (must equal 100%) | C15: =SUM(C5:C14) -> 1
B16: Check | C16: =IF(ROUND(C15,4)=1,"OK","FIX WEIGHTS") -> OK
A18: Scoring scale for every criterion: 0 = absent · 1 = minimal · 2 = partial · 3 = adequate · 4 = strong · 5 = best available anywhere.
A19: Note on C6 (licence): score the RISK-ADJUSTED usability, not the generosity of the wording. Open Food Facts is freely available and scores 1, because share-alike makes it commercially hazardous.

Sheet Scoring Matrix
A1: Scoring matrix — candidate data sources
A2: Scores 0–5 (editable, blue). Weight row links to the Weights tab (green). Weighted / Score % / Rank are formulas. Sorted by weighted score at build time; re-sort manually after editing.
A4: Source | B4: Role | C4: C1 South Indian coverage | D4: C2 Recipe / cooked-dish level | E4: C3 Per-serving & household units | F4: C4 Micronutrient / component depth | G4: C5 Provenance & method docs | H4: C6 Commercial licence clarity | I4: C7 Machine readability / API | J4: C8 Maintenance & update cadence | K4: C9 Regional-language support | L4: C10 Cost to acquire (5 = free) | M4: Weighted (0-5) | N4: Score % | O4: Rank | P4: Verdict / how to use
A5: Weight (edit on 'Weights' tab) → | C5: =Weights!$C$5 -> 0.25 | D5: =Weights!$C$6 -> 0.13 | E5: =Weights!$C$7 -> 0.08 | F5: =Weights!$C$8 -> 0.09 | G5: =Weights!$C$9 -> 0.13 | H5: =Weights!$C$10 -> 0.15 | I5: =Weights!$C$11 -> 0.07 | J5: =Weights!$C$12 -> 0.04 | K5: =Weights!$C$13 -> 0.04 | L5: =Weights!$C$14 -> 0.02 | M5: =SUM(C5:L5) -> 1
A6: Indian Nutrient Databank (INDB) — 1,014 recipes | B6: Recipe database | C6: 2 | D6: 5 | E6: 5 | F6: 4 | G6: 5 | H6: 3 | I6: 5 | J6: 3 | K6: 2 | L6: 5 | M6: =SUMPRODUCT($C6:$L6,$C$5:$L$5) -> 3.66 | N6: =M6/5 -> 0.732 | O6: =RANK(M6,$M$6:$M$30) -> 1 | P6: PRIMARY SUBSTRATE. Only recipe-level Indian database in existence, with per-serving values and a published method. South Indian subset is thin — that gap is Pathyam's Phase 1.
A7: South Indian GI/GL literature corpus | B7: Primary literature | C7: 5 | D7: 4 | E7: 3 | F7: 1 | G7: 5 | H7: 4 | I7: 0 | J7: 0 | K7: 1 | L7: 5 | M7: =SUMPRODUCT($C7:$L7,$C$5:$L$5) -> 3.49 | N7: =M7/5 -> 0.698 | O7: =RANK(M7,$M$6:$M$30) -> 2 | P7: HIGHEST South Indian specificity of anything available. Shakappa 2022 (23 breakfast foods) + IJMR + CFTRI. Manual extraction, ~2 weeks. Clinical differentiator.
A8: ifct2017 npm / Zenodo corpus (Sahu) | B8: Composition (derived) | C8: 4 | D8: 0 | E8: 1 | F8: 5 | G8: 4 | H8: 3 | I8: 5 | J8: 2 | K8: 3 | L8: 5 | M8: =SUMPRODUCT($C8:$L8,$C$5:$L$5) -> 3.15 | N8: =M8/5 -> 0.63 | O8: =RANK(M8,$M$6:$M$30) -> 3 | P8: Machine-readable IFCT with 22 tables incl. local-language names, analytical methods, Jones factors, energy conversion factors. Code is MIT; underlying data rights are NOT.
A9: USDA FNDDS (portion weights) | B9: Portion reference | C9: 0 | D9: 3 | E9: 5 | F9: 3 | G9: 5 | H9: 5 | I9: 5 | J9: 4 | K9: 0 | L9: 5 | M9: =SUMPRODUCT($C9:$L9,$C$5:$L$5) -> 3.07 | N9: =M9/5 -> 0.614 | O9: =RANK(M9,$M$6:$M$30) -> 4 | P9: Gram weights per household measure. Methodological template for the katori/count ontology — do not import the values.
A10: INDB — stage 1 ingredients (n=1,095) | B10: Composition (derived) | C10: 3 | D10: 0 | E10: 2 | F10: 4 | G10: 5 | H10: 3 | I10: 5 | J10: 3 | K10: 2 | L10: 5 | M10: =SUMPRODUCT($C10:$L10,$C$5:$L$5) -> 3.02 | N10: =M10/5 -> 0.604 | O10: =RANK(M10,$M$6:$M$30) -> 5 | P10: IFCT 2017 → IFCT 2004 → CoFID → USDA fallback chain, already resolved. Saves months of matching work.
A11: FSANZ AUSNUT 2011-13 / NUTTAB | B11: Composition (foreign) | C11: 1 | D11: 3 | E11: 4 | F11: 4 | G11: 4 | H11: 5 | I11: 4 | J11: 1 | K11: 0 | L11: 5 | M11: =SUMPRODUCT($C11:$L11,$C$5:$L$5) -> 3.01 | N11: =M11/5 -> 0.602 | O11: =RANK(M11,$M$6:$M$30) -> 6 | P11: CC-BY. Contains Indian-cuisine composite dishes from the Australian survey — useful independent cross-check on your computed recipe values.
A12: USDA FoodData Central | B12: Composition (foreign) | C12: 0 | D12: 2 | E12: 4 | F12: 4 | G12: 5 | H12: 5 | I12: 5 | J12: 5 | K12: 0 | L12: 5 | M12: =SUMPRODUCT($C12:$L12,$C$5:$L$5) -> 2.99 | N12: =M12/5 -> 0.598 | O12: =RANK(M12,$M$6:$M$30) -> 7 | P12: Best-engineered FCT in the world; zero South Indian relevance. Use strictly for gap-fill ingredients and as an API design reference.
A13: UK CoFID 2021 (McCance & Widdowson) | B13: Composition (foreign) | C13: 1 | D13: 2 | E13: 3 | F13: 4 | G13: 5 | H13: 5 | I13: 4 | J13: 2 | K13: 0 | L13: 5 | M13: =SUMPRODUCT($C13:$L13,$C$5:$L$5) -> 2.97 | N13: =M13/5 -> 0.594 | O13: =RANK(M13,$M$6:$M$30) -> 8 | P13: OGL v3 — cleanest licence of any major FCT. INDB already borrows 144 ingredients from it. Some South Asian items via the UK diet.
A14: Danish Frida (DTU Food) | B14: Composition (foreign) | C14: 0 | D14: 2 | E14: 3 | F14: 5 | G14: 5 | H14: 5 | I14: 5 | J14: 4 | K14: 0 | L14: 5 | M14: =SUMPRODUCT($C14:$L14,$C$5:$L$5) -> 2.96 | N14: =M14/5 -> 0.592 | O14: =RANK(M14,$M$6:$M$30) -> 9 | P14: Excellent micronutrient depth and open licence. Gap-fill only.
A15: ICMR-NIN IFCT 2017 | B15: Composition (reference) | C15: 4 | D15: 0 | E15: 1 | F15: 5 | G15: 5 | H15: 2 | I15: 2 | J15: 1 | K15: 3 | L15: 5 | M15: =SUMPRODUCT($C15:$L15,$C$5:$L$5) -> 2.88 | N15: =M15/5 -> 0.576 | O15: =RANK(M15,$M$6:$M$30) -> 10 | P15: The authoritative Indian table and the source of truth — but raw-ingredient only and regionally composited. Structurally cannot answer 'how many calories in this dosa'.
A16: HealthifyMe | B16: Competitor benchmark | C16: 5 | D16: 5 | E16: 5 | F16: 2 | G16: 0 | H16: 0 | I16: 0 | J16: 5 | K16: 4 | L16: 0 | M16: =SUMPRODUCT($C16:$L16,$C$5:$L$5) -> 2.84 | N16: =M16/5 -> 0.568 | O16: =RANK(M16,$M$6:$M$30) -> 11 | P16: THE INSTRUCTIVE ROW: maximum coverage, zero provenance, zero licence. Proves breadth alone is not a moat — and is unusable for clinical or research work.
A17: FAO/INFOODS guidelines + compilation tool 1.2.1 | B17: Method / standard | C17: 0 | D17: 3 | E17: 2 | F17: 3 | G17: 5 | H17: 5 | I17: 3 | J17: 3 | K17: 1 | L17: 5 | M17: =SUMPRODUCT($C17:$L17,$C$5:$L$5) -> 2.69 | N17: =M17/5 -> 0.538 | O17: =RANK(M17,$M$6:$M$30) -> 12 | P17: MANDATORY. Tagnames, food matching, data checking, recipe calculation. Adopt before writing a single row.
... A30: Bognár (2002) yield & retention tables | B30: Cooking factors | C30: 0 | D30: 0 | E30: 0 | F30: 3 | G30: 4 | H30: 2 | I30: 1 | J30: 0 | K30: 0 | L30: 2 | M30: =SUMPRODUCT($C30:$L30,$C$5:$L$5) -> 1.2 | N30: =M30/5 -> 0.24 | O30: =RANK(M30,$M$6:$M$30) -> 25 | P30: Second retention source for cross-checking USDA R6. Print publication; harder to obtain.
A32: Excluded from scoring by design: regulators (FSSAI, FDA, EFSA, MHRA, TGA), reference standards (ICMR RDA 2020, DGI 2024), consumption surveys (NNMB/NFHS-5/CNNS), and tooling (AI4Bharat, image datasets). They are essential to the project but are not candidate composition sources — scoring them on 'South Indian dish coverage' would be meaningless. All are catalogued on 'Source Master' with a reason.

Sheet Source Master
A1: Source master catalogue — all 36 sources
A2: Includes sources deliberately excluded from the scoring matrix, with the reason stated in the Notes column.
A4: Source | B4: Custodian | C4: Role | D4: Scope / size | E4: Access method | F4: Licence | G4: Cost | H4: Last updated | I4: URL | J4: Notes / why scored or not
A5: ICMR-NIN IFCT 2017 | B5: ICMR-National Institute of Nutrition, Hyderabad | C5: Composition (reference) | D5: 528 foods x 151 components; 6-region composite sampling | E5: Free PDF; npm/Zenodo corpus; Kaggle mirror | F5: Not stated — ICMR copyright | G5: Free to read | H5: 2017 | I5: https://www.nin.res.in/ebooks/IFCT2017.pdf | J5: Raw ingredients only. Regional averaging is the core structural problem for Pathyam.
A6: ifct2017 npm / Zenodo corpus | B6: Subhajit Sahu (wolfram77), community | C6: Composition (derived) | D6: 22 tables: compositions, columns, descriptions, methods, energies, jonesFactors, regions, intakes... | E6: npm, unpkg, jsDelivr, Zenodo zip | F6: npm packages MIT; Zenodo v2.0.10 'Other (Open)' | G6: Free | H6: v2.0.10, Sep 2022 | I6: https://zenodo.org/records/7088653 | J6: `descriptions` module carries Tam./Tel./Mal./Kan. food names — free seed for the lexicon.
A7: ICMR-NIN IFCT 2004 (Gopalan et al.) | B7: ICMR-NIN | C7: Composition (legacy) | D7: Nutritive Value of Indian Foods, revised edn | E7: Request from NIN | F7: ICMR copyright | G7: Request | H7: 2004 rev. | I7: https://www.nin.res.in/ | J7: INDB uses it for gap-fill. Tier C confidence.
A8: Indian Nutrient Databank (INDB) | B8: Anuvaad Solutions LLP / Univ. of Edinburgh (Jaacks) | C8: Recipe database | D8: 1,095 ingredients + 1,014 recipes; per-100g AND per-serving | E8: Direct xlsx download; Stata code on GitHub | F8: Described 'open access'; no explicit licence file | G8: Free | H8: Nov 2024 build | I8: https://www.anuvaad.org.in/indian-nutrient-databank/ | J8: Gates-funded. Method paper: Curr Dev Nutr 2024;103790. CONFIRM COMMERCIAL TERMS IN WRITING.
A9: INDB code repository | B9: lindsayjaacks (GitHub) | C9: Method / code | D9: INDB.do (Stata), UK_fct, US_fct, recipes, units, servingsize, USDA_nrf | E9: GitHub clone | F9: No LICENSE file present | G9: Free | H9: 54 commits | I9: https://github.com/lindsayjaacks/Indian-Nutrient-Databank-INDB- | J9: Port to Python as your recipe-engine validation harness. Ships derived data, not licensed inputs.
A10: Nutrify India Now 2.0 | B10: ICMR-NIN | C10: App / benchmark | D10: IFCT-based; search in 17 languages; 6 food groups; BMR/BMI/energy balance | E10: Google Play | F10: App EULA — no data reuse | G10: Free | H10: 2.0 | I10: https://play.google.com/store/apps/details?id=com.nin20.nin2byo2i | J10: NOT SCORED as a data source — no reuse rights. Use as language-coverage benchmark and validation oracle.
A11: ICMR RDA 2020 | B11: ICMR Expert Group | C11: Reference standard (targets) | D11: RDA/EAR by age, sex, physiological state | E11: Published report | F11: Government publication | G11: Free | H11: 2020 | I11: https://www.nin.res.in/ | J11: NOT SCORED — it sets targets, not composition. Legally operative: FSSAI mandated it from 1 Jul 2023. Use instead of US DRIs.
A12: Dietary Guidelines for Indians 2024 | B12: ICMR-NIN | C12: Reference standard (diet quality) | D12: 17 guidelines; My Plate; min. 8 food groups | E12: Free PDF | F12: Government publication | G12: Free | H12: May 2024 | I12: https://nin.res.in/dietaryguidelines/pdfjs/locale/DGI_2024.pdf | J12: NOT SCORED — scaffold for the diet-quality score. Government-aligned metric no competitor uses.
A13: FSS (Labelling & Display) Regulations 2020 | B13: FSSAI | C13: Regulation | D13: Compendium version VII | E13: Free PDF | F13: Government publication | G13: Free | H13: 03 Apr 2025 | I13: https://fssai.gov.in/upload/uploadfiles/files/Comp_Labelling%20Display_Version%20VII_03042025.pdf | J13: NOT SCORED — regulator, not a data source. Binds you the moment Pathyam renders a nutrition panel.
A14: FSSAI RDA declaration direction (2022) | B14: FSSAI | C14: Regulation | D14: % RDA in bold for sugar, sat fat, sodium; claim thresholds >=15% / >=30% | E14: Free PDF | F14: Government publication | G14: Free | H14: Mar 2022 | I14: https://www.fssai.gov.in/upload/advisories/2022/03/6243ef28079ceDirection_Nutra_30_03_2022.pdf | J14: NOT SCORED. Governs any claim language in-app.
A15: Indian Nutrition Rating (INR) / FOPNL | B15: FSSAI | C15: Regulation | D15: 1/2 to 5 star front-of-pack rating | E15: Regulation text | F15: Government publication | G15: Free | H15: Ongoing | I15: https://www.fssai.gov.in/ | J15: NOT SCORED. If Pathyam computes an INR score it must match FSSAI's algorithm exactly.
... A40: DPDP Act 2023 + DPDP Rules 2025 | B40: MeitY, Government of India | C40: Regulation (data) | D40: Rules notified 13 Nov 2025; phased compliance to 13 May 2027; 7-year consent records | E40: Free PDF | F40: Government publication | G40: Free | H40: Nov 2025 | I40: https://www.meity.gov.in/static/uploads/2024/06/2bf1f0e9f04e6fb4f8fef35e82c42aa5.pdf | J40: NOT A DATA SOURCE. Governs every user record Pathyam stores. Privacy-by-design from Phase 2.

Sheet Licence & Risk
A1: Licence position and risk register
A2: Ordered by severity. The top two rows are the ones that can materially damage the project. Update Status as items close.
A4: Source | B4: Licence | C4: Share-alike? | D4: Commercial use | E4: Risk | F4: Specific risk | G4: Mitigation | H4: Action required | I4: Owner | J4: Status
A5: Open Food Facts | B5: ODbL v1.0 | C5: YES | D5: Permitted but viral | E5: CRITICAL | F5: Share-alike: combining OFF into a derived database obliges you to release that database as open data — destroying Pathyam-DB's commercial value. | G5: Physical isolation. Separate service, separate schema. Runtime query only. Never write OFF values into composition_value or any export. | H5: Write an architecture decision record; add a CI check that OFF identifiers never appear in core exports. | I5: Eng | J5: Not started
A6: ICMR-NIN IFCT 2017 / 2004 | B6: Not stated (ICMR copyright) | C6: No | D6: UNCLEAR | E6: CRITICAL | F6: Free-to-read is not free-to-commercialise. Building product on undefined rights to the national reference table is the single largest silent risk in the project. | G6: Written permission from ICMR-NIN with explicit commercial terms. Fallback: derive values from primary literature plus your own lab panel; use IFCT only as an unpublished cross-check. | H6: Letter to ICMR-NIN, Hyderabad — combine with the GI collaboration ask to Dept of Dietetics. | I6: Founder | J6: Not started
A7: Indian Nutrient Databank (INDB) | B7: Described 'open access'; no licence file | C7: Unknown | D7: UNCLEAR | E7: HIGH | F7: Portal says open access but publishes no CC/ODbL declaration. Commercial derivative rights are undefined. | G7: Written clarification from Anuvaad Solutions LLP. Fallback: use only the published method (freely usable) and rebuild recipes from your own sources. | H7: Email awasthi@anuvaad.org.in requesting written licence terms. | I7: Founder | J7: Not started
A8: INDB source cookbooks | B8: Copyright (Elite Publishing; Orient BlackSwan) | C8: No | D8: No | E8: MEDIUM | F8: 868 of INDB's 1,014 recipes come from two copyrighted textbooks. INDB used them under research use; a commercial derivative is a different posture. | G8: Ingredient quantities are facts and generally not copyrightable; the expression is. Never reproduce recipe text. Build Pathyam's own South Indian recipes from field collection and open sources. | H8: Legal opinion on derived-data position before Phase 3 launch. | I8: Founder + counsel | J8: Not started
A9: ifct2017 npm / Zenodo corpus | B9: npm MIT; Zenodo 'Other (Open)' | C9: No | D9: Code yes; data unclear | E9: HIGH | F9: The MIT licence covers the packaging code. It cannot grant rights the packager did not hold over ICMR's underlying data. | G9: Treat as a convenient reader for data you have separately licensed from NIN. Do not rely on MIT as your data licence. | H9: Resolve alongside the ICMR-NIN permission. | I9: Founder | J9: Not started
A10: USDA FoodData Central / Retention Factors R6 | B10: US Government work (public domain) | C10: No | D10: YES — unrestricted | E10: LOW | F10: None. Attribution is courtesy, not obligation. | G10: Use freely. Attribute anyway — it costs nothing and supports the provenance story. | H10: Register for an API key. | I10: Eng | J10: Not started
A11: UK CoFID 2021 | B11: Open Government Licence v3 | C11: No | D11: YES with attribution | E11: LOW | F11: None material. | G11: Attribute per OGL v3. | H11: Download and record attribution string in source table. | I11: Eng | J11: Not started
A12: FSANZ AUSNUT / NUTTAB | B12: CC-BY | C12: No | D12: YES with attribution | E12: LOW | F12: None material. | G12: Attribute per CC-BY. | H12: Optional — cross-validation only. | I12: Eng | J12: Not started
A13: Danish Frida / Norwegian Matvaretabellen / Health Canada CNF | B13: Open / OGL-Canada | C13: No | D13: YES with attribution | E13: LOW | F13: None material. | G13: Attribute. | H13: Gap-fill as needed. | I13: Eng | J13: Not started
A14: FAO/INFOODS guidelines & tools | B14: FAO terms — free use | C14: No | D14: YES | E14: LOW | F14: None. Methodology, not data. | G14: Cite in the methods paper. | H14: Adopt tagnames before schema freeze. | I14: Eng | J14: Not started
A15: South Indian GI literature | B15: Journal copyright; PMC open access | C15: No | D15: Facts yes; figures per licence | E15: LOW | F15: Numerical findings are facts and freely citable. Reproducing figures or tables verbatim needs the publisher's licence. | G15: Extract values into your own structured table with PMID/DOI provenance. Do not copy typeset tables. | H15: Systematic extraction starting from PMID 35875218 citation graph. | I15: Founder | J15: Not started
... A20: Indian food image datasets | B20: Varies per dataset | C20: Varies | D20: Varies | E20: MEDIUM | F20: Roboflow and academic sets carry heterogeneous licences; some are non-commercial. | G20: Audit each dataset's licence individually before any training use. Prefer VLM + retrieval over training, which sidesteps most of this. | H20: Audit at Phase 3 kickoff. | I20: Eng | J20: Not started
A22: Open items | B22: =COUNTIF(J5:J20,"Not started") -> 16
A23: Critical items open | B23: =SUMPRODUCT((E5:E20="CRITICAL")*(J5:J20<>"Closed")) -> 3

Sheet Acquisition Tracker
A1: Acquisition & clearance tracker — Phase 0
A2: Sequenced actions for the first six weeks. Edit the yellow Status column; the summary below updates automatically.
A4: # | B4: Action | C4: Source(s) | D4: Category | E4: Owner | F4: Target | G4: Status | H4: Blocker | I4: Notes
A5: 1 | B5: Letter to ICMR-NIN Hyderabad: (a) IFCT 2017+2004 commercial terms, (b) GI collaboration with Dept of Dietetics | C5: IFCT 2017/2004; GI literature | D5: Legal + Partnership | E5: Founder | F5: Week 1 | G5: Not started | I5: Highest-leverage single action. Shakappa et al. are at the same institute that holds IFCT.
A6: 2 | B6: Email Anuvaad Solutions LLP (awasthi@anuvaad.org.in) requesting written INDB licence terms | C6: INDB | D6: Legal | E6: Founder | F6: Week 1 | G6: Not started | I6: Blocks all Phase 1 product work if it comes back restrictive.
A7: 3 | B7: Download Anuvaad_INDB_2024.11.xlsx and profile it — count genuinely South Indian recipes | C7: INDB | D7: Acquisition | E7: Eng | F7: Week 1 | G7: Not started | I7: Quantifies the actual size of the gap Pathyam fills.
A8: 4 | B8: Clone INDB GitHub repo; read INDB.do end to end | C8: INDB code | D8: Acquisition | E8: Eng | F8: Week 1 | G8: Not started | I8: Understand the fallback chain and retention-factor mapping before porting.
A9: 5 | B9: Register for USDA FoodData Central API key; pull FNDDS portion weights and Retention Factors R6 | C9: USDA FDC; FNDDS; NRF R6 | D9: Acquisition | E9: Eng | F9: Week 2 | G9: Not started | I9: Public domain — no legal gate.
A10: 6 | B10: Download CoFID 2021 (OGL v3) and all FAO/INFOODS guidelines + compilation tool 1.2.1 | C10: CoFID; FAO/INFOODS | D10: Acquisition | E10: Eng | F10: Week 2 | G10: Not started | I10: Adopt tagnames before schema freeze.
A11: 7 | B11: Systematic literature extraction for South Indian GI/GL, starting from PMID 35875218 citation graph | C11: GI literature | D11: Research | E11: Founder | F11: Weeks 2-4 | G11: Not started | I11: ~2 weeks. Clinical differentiator for Phase 2.
A12: 8 | B12: Draft seed dish list: 150 dishes x 4 states with named regional variants | C12: n/a — original work | D12: Research | E12: Founder + culinary advisor | F12: Weeks 2-4 | G12: Not started | I12: Defines Phase 1 scope. Include Sadya, tiffin variants, Andhra pickles, ragi preparations.
A13: 9 | B13: Stand up DuckDB + dbt + Great Expectations skeleton with QC gates 1-8 | C13: n/a — infrastructure | D13: Engineering | E13: Eng | F13: Weeks 3-4 | G13: Not started | I13: See dossier section 4.
A14: 10 | B14: Write the ODbL-boundary architecture decision record and add the CI check | C14: Open Food Facts | D14: Engineering + Legal | E14: Eng | F14: Week 3 | G14: Not started | I14: Cheap now; unfixable in year three.
A15: 11 | B15: Port INDB.do to Python and reproduce all 1,014 recipes within rounding tolerance | C15: INDB | D15: Engineering | E15: Eng | F15: Weeks 4-6 | G15: Not started | H15: Depends on #3, #4 | I15: Best integration test available, and it is free.
A16: 12 | B16: Scope a NABL-accredited lab quote (CSIR-CFTRI Mysuru / NIN) for a 30-50 dish analytical panel | C16: n/a — primary data | D16: Partnership | E16: Founder | F16: Week 4 | G16: Not started | I16: Prioritise fermented batters, coconut-milk preparations, deep-fried oil absorption, Andhra pickle sodium.
A17: 13 | B17: Identify grant route — ICMR, DBT/BIRAC, Wellcome-DBT India Alliance | C17: n/a — funding | D17: Funding | E17: Founder | F17: Weeks 4-6 | G17: Not started | I17: Gates funded Anuvaad's INDB — precedent exists for this exact kind of work.
A18: 14 | B18: Build the four-language lexicon seed from ifct2017 `descriptions` + IndicXlit, then human-verify | C18: ifct2017 corpus; AI4Bharat | D18: Engineering | E18: Eng | F18: Weeks 5-8 | G18: Not started | H18: Depends on #1 | I18: IFCT already carries romanised Tam./Tel./Mal./Kan. names — do not start from zero.
A19: 15 | B19: Legal opinion on the derived-data position for recipe-derived nutrient values | C19: INDB source cookbooks | D19: Legal | E19: Founder + counsel | F19: Week 6 | G19: Not started | I19: Needed before any commercial launch, not before development.
B21: Total actions | C21: =COUNTA(A5:A19) -> 15
B22: Done | C22: =COUNTIF(G5:G19,"Done") -> 0
B23: In progress | C23: =COUNTIF(G5:G19,"In progress") -> 0
B24: Blocked | C24: =COUNTIF(G5:G19,"Blocked") -> 0
B25: % complete | C25: =IFERROR(C22/C21,0) -> 0
